<?xml version="1.0" encoding="UTF-8"?>
<ROOT>
    <delegue etat="NOMME" id="1679584" login="GVERGEZ">
        <identite civilite="Monsieur" codeDep="75">
            <nom>VERGEZ</nom>
            <prenom>Georges</prenom>
        </identite>
        <email>georges.vergez@defenseurdesdroits.fr</email>
        <photo>GVERGEZ.jpg</photo>
        <structures>
            <structure principal="OUI">
                <libelle>Maison de justice et du droit du 14ème arrondissement</libelle>
                <libelleSecondaire />
                <adresse>6, rue Bardinet</adresse>
                <boitePostale />
                <tel>01 45 45 22 23</tel>
                <fax>01 45 40 01 42</fax>
                <ville cp="75014"><value>PARIS - 14</value></ville>
                <poi>
                    <longitude>2.316886</longitude>
                    <latitude>48.830773</latitude>
                </poi>
                <permanences>
                    <permanence>
                        <jour>MARDI</jour>
                        <horaire>JOURNEE</horaire>
                    </permanence>
                    <permanence>
                        <jour>LUNDI
</jour>
                        <horaire>JOURNEE</horaire>
                    </permanence>
                </permanences>
            </structure>
        </structures>
    </delegue>
</ROOT>
